kraken_thing_simple/__init__.py
kraken_thing_simple/kraken_thing_simple.py
kraken_thing_simple-0.0.5.dist-info/LICENSE.txt
kraken_thing_simple-0.0.5.dist-info/METADATA
kraken_thing_simple-0.0.5.dist-info/WHEEL
kraken_thing_simple-0.0.5.dist-info/top_level.txt
kraken_thing_simple-0.0.5.dist-info/RECORD
