Metadata-Version: 2.1
Name: kraken-thing-simple
Version: 0.0.5
Summary: Kraken Simple Thing Class
Home-page: https://github.com/tactik8/kraken_class_thing
Author: Tactik8
Author-email: info@tactik8.com
License: MIT
Classifier: License :: OSI Approved :: MIT License
Classifier: Programming Language :: Python :: 3
Classifier: Programming Language :: Python :: 3.8
License-File: LICENSE.txt
